MANIFEST.in
README.rst
setup.py
pubmed_embedding/__init__.py
pubmed_embedding/__version__.py
pubmed_embedding/pubmed_embedding.py
pubmed_embedding/utils.py
pubmed_embedding.egg-info/PKG-INFO
pubmed_embedding.egg-info/SOURCES.txt
pubmed_embedding.egg-info/dependency_links.txt
pubmed_embedding.egg-info/requires.txt
pubmed_embedding.egg-info/top_level.txt
pubmed_embedding/versions/pubmed_bert_30_11_2022.json
pubmed_embedding/versions/pubmed_scibert_30_11_2022.json
pubmed_embedding/versions/pubmed_specter_30_11_2022.json